Workbook
Name Code: List!$A$1:$A$14

Sheet Expense Report
C2: Avant Ministries
C3: Expense Report 2026
C7: Name | G7: Date submitted
C10: Account/Project number (one per report) | G10: Field
D13: Total expenses | H13: =H154 -> 0
D15: Advanced funds received | H15: =-H37 -> 0
D17: Funds received directly | H17: =-H165 -> 0
D19: Balance due to worker | H19: =H13+H15+H17 -> 0
D21: (Taxable Total | H21: =SUMIF(J42:J56,"x",H42:H56)+SUMIF(J61:J75,"x",H61:H75)+SUMIF(J80:J104,"x",H80:H104)+SUMIF(J111:J151,"x",H111:H151) -> 0 | I21: )
C25: Worker signature | G25: Date
C28: Supervisor approval | G28: Title
C31: Accounting approval
A34: Advanced Funds Received
H35: Amount
B36: Date Received | D36: Amount and Explanation of Advance | H36: to be Cleared
A39: Travel - air, bus, taxi (attach receipts for amounts over $75, please mark dependent travel as taxable) | M39: Optional
F40: Cost in USD or | G40: Exchange Rate | H40: Cost in | J40: Taxable | K40: Advanced | M40: Accounting Code
B41: Date | C41: From | D41: To | E41: Ministry Purpose | F41: Local Currency | G41: Local To USD | H41: USD | J41: "x" | K41: "x" | M41: (Select from Dropdown)
A42: 1 | H42: =IF(F42>0,IF(G42>0, (F42*G42),IF(#REF!>0,F42/#REF!,F42)),"")
A43: 2
A44: 3 | H44: =IF(F44>0,IF(G44>0, (F44*G44),IF(#REF!>0,F44/#REF!,F44)),"")
A45: 4 | H45: =IF(F45>0,IF(G45>0, (F45*G45),IF(#REF!>0,F45/#REF!,F45)),"")
A46: 5 | H46: =IF(F46>0,IF(G46>0, (F46*G46),IF(#REF!>0,F46/#REF!,F46)),"")
A47: 6 | H47: =IF(F47>0,IF(G47>0, (F47*G47),IF(#REF!>0,F47/#REF!,F47)),"")
A48: 7 | H48: =IF(F48>0,IF(G48>0, (F48*G48),IF(#REF!>0,F48/#REF!,F48)),"")
A49: 8 | H49: =IF(F49>0,IF(G49>0, (F49*G49),IF(#REF!>0,F49/#REF!,F49)),"")
A50: 9 | H50: =IF(F50>0,IF(G50>0, (F50*G50),IF(#REF!>0,F50/#REF!,F50)),"")
A51: 10 | H51: =IF(F51>0,IF(G51>0, (F51*G51),IF(#REF!>0,F51/#REF!,F51)),"")
A52: 11 | H52: =IF(F52>0,IF(G52>0, (F52*G52),IF(#REF!>0,F52/#REF!,F52)),"")
A53: 12 | H53: =IF(F53>0,IF(G53>0, (F53*G53),IF(#REF!>0,F53/#REF!,F53)),"")
A54: 13 | H54: =IF(F54>0,IF(G54>0, (F54*G54),IF(#REF!>0,F54/#REF!,F54)),"")
A55: 14 | H55: =IF(F55>0,IF(G55>0, (F55*G55),IF(#REF!>0,F55/#REF!,F55)),"")
A56: 15 | H56: =IF(F56>0,IF(G56>0, (F56*G56),IF(#REF!>0,F56/#REF!,F56)),"")
A58: Ministry Entertainment (attach receipts for amounts over $75, please mark dependent entertainment as taxable): | M58: Optional
F59: Cost in USD or | G59: Exchange Rate | H59: Cost in | J59: Taxable | K59: Advanced | M59: Accounting
B60: Date | C60: Who | D60: Where | E60: Ministry Purpose | F60: Local Currency | G60: Local To USD | H60: USD | J60: "x" | K60: "x" | M60: Code
A61: 16 | H61: =IF(F61>0,IF(G61>0, (F61*G61),IF(#REF!>0,F61/#REF!,F61)),"")
A62: 17 | H62: =IF(F62>0,IF(G62>0, (F62*G62),IF(#REF!>0,F62/#REF!,F62)),"")
A63: 18 | H63: =IF(F63>0,IF(G63>0, (F63*G63),IF(#REF!>0,F63/#REF!,F63)),"")
A64: 19 | H64: =IF(F64>0,IF(G64>0, (F64*G64),IF(#REF!>0,F64/#REF!,F64)),"")
A65: 20 | H65: =IF(F65>0,IF(G65>0, (F65*G65),IF(#REF!>0,F65/#REF!,F65)),"")
A66: 21 | H66: =IF(F66>0,IF(G66>0, (F66*G66),IF(#REF!>0,F66/#REF!,F66)),"")
A67: 22 | H67: =IF(F67>0,IF(G67>0, (F67*G67),IF(#REF!>0,F67/#REF!,F67)),"")
A68: 23 | H68: =IF(F68>0,IF(G68>0, (F68*G68),IF(#REF!>0,F68/#REF!,F68)),"")
A69: 24 | H69: =IF(F69>0,IF(G69>0, (F69*G69),IF(#REF!>0,F69/#REF!,F69)),"")
A70: 25 | H70: =IF(F70>0,IF(G70>0, (F70*G70),IF(#REF!>0,F70/#REF!,F70)),"")
A71: 26 | H71: =IF(F71>0,IF(G71>0, (F71*G71),IF(#REF!>0,F71/#REF!,F71)),"")
A72: 27 | H72: =IF(F72>0,IF(G72>0, (F72*G72),IF(#REF!>0,F72/#REF!,F72)),"")
... A75: 30 | H75: =IF(F75>0,IF(G75>0, (F75*G75),IF(#REF!>0,F75/#REF!,F75)),"")
A77: Automobile Mileage (please mark dependent travel as taxable): | M77: Optional
F78: Miles | G78: Kilometers | H78: Cost in | J78: Taxable | K78: Advanced | M78: Accounting
B79: Date | C79: From | D79: To | E79: Ministry Purpose | F79: 0.725 | G79: 0.45 | H79: In USD | J79: "x" | K79: "x" | M79: Code
A80: 31 | H80: =IF(F80>0,F80*0.725,IF(G80>0,G80*0.45," "))
A81: 32 | H81: =IF(F81>0,F81*0.725,IF(G81>0,G81*0.45," "))
A82: 33 | H82: =IF(F82>0,F82*0.725,IF(G82>0,G82*0.45," "))
A83: 34 | H83: =IF(F83>0,F83*0.725,IF(G83>0,G83*0.45," "))
A84: 35 | H84: =IF(F84>0,F84*0.725,IF(G84>0,G84*0.45," "))
A85: 36 | H85: =IF(F85>0,F85*0.725,IF(G85>0,G85*0.45," "))
A86: 37 | H86: =IF(F86>0,F86*0.725,IF(G86>0,G86*0.45," "))
A87: 38 | H87: =IF(F87>0,F87*0.725,IF(G87>0,G87*0.45," "))
A88: 39 | H88: =IF(F88>0,F88*0.725,IF(G88>0,G88*0.45," "))
A89: 40 | H89: =IF(F89>0,F89*0.725,IF(G89>0,G89*0.45," "))
A90: 41 | H90: =IF(F90>0,F90*0.725,IF(G90>0,G90*0.45," "))
A91: 42 | H91: =IF(F91>0,F91*0.725,IF(G91>0,G91*0.45," "))
... A104: 55 | H104: =IF(F104>0,F104*0.725,IF(G104>0,G104*0.45," "))
C106: 1 | E106: Total Distance: | F106: =SUM(F80:F104) -> 0 | G106: =SUM(G80:G104) -> 0
A108: Other Expenses (attach receipts for amounts over $75, please mark setup and dependent expense as taxable): | M108: Optional
F109: Cost in USD or | G109: Exchange Rate | H109: Cost in | J109: Taxable | K109: Advanced | M109: Accounting
B110: Date | C110: Description & Ministry Purpose | F110: Local Currency | G110: Local To USD | H110: USD | J110: "x" | K110: "x" | M110: Code
A111: 56 | H111: =IF(F111>0,IF(G111>0, (F111*G111),IF(#REF!>0,F111/#REF!,F111)),"")
A112: 57 | H112: =IF(F112>0,IF(G112>0, (F112*G112),IF(#REF!>0,F112/#REF!,F112)),"")
A113: 58 | H113: =IF(F113>0,IF(G113>0, (F113*G113),IF(#REF!>0,F113/#REF!,F113)),"")
A114: 59 | H114: =IF(F114>0,IF(G114>0, (F114*G114),IF(#REF!>0,F114/#REF!,F114)),"")
A115: 60 | H115: =IF(F115>0,IF(G115>0, (F115*G115),IF(#REF!>0,F115/#REF!,F115)),"")
A116: 61 | H116: =IF(F116>0,IF(G116>0, (F116*G116),IF(#REF!>0,F116/#REF!,F116)),"")
A117: 62 | H117: =IF(F117>0,IF(G117>0, (F117*G117),IF(#REF!>0,F117/#REF!,F117)),"")
A118: 63 | H118: =IF(F118>0,IF(G118>0, (F118*G118),IF(#REF!>0,F118/#REF!,F118)),"")
A119: 64 | H119: =IF(F119>0,IF(G119>0, (F119*G119),IF(#REF!>0,F119/#REF!,F119)),"")
A120: 66 | H120: =IF(F120>0,IF(G120>0, (F120*G120),IF(#REF!>0,F120/#REF!,F120)),"")
A121: 65 | H121: =IF(F121>0,IF(G121>0, (F121*G121),IF(#REF!>0,F121/#REF!,F121)),"")
A122: 66 | H122: =IF(F122>0,IF(G122>0, (F122*G122),IF(#REF!>0,F122/#REF!,F122)),"")
... A148: 92 | H148: =IF(F148>0,IF(G148>0, (F148*G148),IF(#REF!>0,F148/#REF!,F148)),"")
A149: 93
A150: 94 | H150: =IF(F150>0,IF(G150>0, (F150*G150),IF(#REF!>0,F150/#REF!,F150)),"")
A151: 95 | H151: =IF(F151>0,IF(G151>0, (F151*G151),IF(#REF!>0,F151/#REF!,F151)),"")
G154: TOTAL EXPENSES (listed on top of page) $ | H154: =SUM(H42:H56, H61:H75, H80:H104, H111:H151) -> 0
A157: Honorariums, offering and ministry gifts received directly (do not list contributions sent to home office or advances received):
B159: Date | C159: From Whom | E159: Address | H159: Amount
A160: 96
A161: 97
A162: 98
A163: 99
A164: 100
G165: Total Received | H165: =SUM(H160:H164) -> 0
B169: ALLOWABLE MINISTRY EXPENSES | G169: NOT ALLOWABLE
A171: 1) | B171: HMA and field travel | F171: 1) | G171: Food (except while traveling), clothing, other personal items
A172: 2) | B172: Household equipment that will be used in Avant-owned property and | F172: 2) | G172: Medical expenses (except for visa)
B173: will remain Avant property | F173: 3) | G173: Personal trips home for wedding, graduations, funerals
A174: 3) | B174: Field equipment: computers, musical instruments | F174: 4) | G174: Travel/Milage while commuting from home to regular place of ministry
A175: 4) | B175: up to 50% of monthly internet and phone expenses | F175: 5) | G175: Storage of personal items while on furlough
...

Sheet Totals
A1: =IF('Expense Report'!C9=0,"No number entered",'Expense Report'!C9) -> No number entered | B1: =IF('Expense Report'!C6=0,"No name entered",'Expense Report'!C6) -> No name entered
B3: Amount
A4: 8401 - Salary | B4: =SUMIF('Expense Report'!$M$37:$M$129,A4,'Expense Report'!$H$37:$H$129) -> 0
A5: 8407 - Utilities | B5: =SUMIF('Expense Report'!$M$37:$M$129,A5,'Expense Report'!$H$37:$H$129) -> 0
A6: 8420 - Travel | B6: =SUMIF('Expense Report'!$M$37:$M$129,A6,'Expense Report'!$H$37:$H$129) -> 0
A7: 8433 - Printing | B7: =SUMIF('Expense Report'!$M$37:$M$129,A7,'Expense Report'!$H$37:$H$129) -> 0
A8: 8434 - Office Supplies | B8: =SUMIF('Expense Report'!$M$37:$M$129,A8,'Expense Report'!$H$37:$H$129) -> 0
A9: 8435 - Food | B9: =SUMIF('Expense Report'!$M$37:$M$129,A9,'Expense Report'!$H$37:$H$129) -> 0
A10: 8440 - Office Equipment | B10: =SUMIF('Expense Report'!$M$37:$M$129,A10,'Expense Report'!$H$37:$H$129) -> 0
A11: 8441 - Computers & Technology | B11: =SUMIF('Expense Report'!$M$37:$M$129,A11,'Expense Report'!$H$37:$H$129) -> 0
A12: 8451 - Construction | B12: =SUMIF('Expense Report'!$M$37:$M$129,A12,'Expense Report'!$H$37:$H$129) -> 0
A13: 8457 - Postage | B13: =SUMIF('Expense Report'!$M$37:$M$129,A13,'Expense Report'!$H$37:$H$129) -> 0
A14: 8459 - Legal & Audit | B14: =SUMIF('Expense Report'!$M$37:$M$129,A14,'Expense Report'!$H$37:$H$129) -> 0
A15: 8464 - Meals & Entertainment | B15: =SUMIF('Expense Report'!$M$37:$M$129,A15,'Expense Report'!$H$37:$H$129) -> 0
... A17: 8473 - Training | B17: =SUMIF('Expense Report'!$M$37:$M$129,A17,'Expense Report'!$H$37:$H$129) -> 0
A19: 5100.001 - Contributions | B19: =-'Expense Report'!H165 -> 0
A21: 2199.150 - Taxable | B21: =-'Expense Report'!H21 -> 0
A22: 2010.150 - Taxable | B22: ='Expense Report'!H21 -> 0
A24: 2010.114 - Advance | B24: =-'Expense Report'!H37 -> 0
A26: Total | B26: =SUM(B4:B24) -> 0

Sheet List
A1: 8401 - Salary
A2: 8407 - Utilities
A3: 8420 - Travel
A4: 8433 - Printing
A5: 8434 - Office Supplies
A6: 8435 - Food
A7: 8440 - Office Equipment
A8: 8441 - Computers & Technology
A9: 8451 - Construction
A10: 8457 - Postage
A11: 8459 - Legal & Audit
A12: 8464 - Meals & Entertainment
... A14: 8473 - Training
